charts/__init__.py
charts/admin.py
charts/apps.py
charts/models.py
charts/urls.py
charts/utils.py
charts/views.py
charts/management/commands/__init__.py
charts/management/commands/create_charts.py
charts/management/commands/create_charttypes.py
charts/management/commands/delete_charts.py
charts/management/commands/delete_charttypes.py
charts/migrations/0001_initial.py
charts/migrations/0002_chartconfig_app_name.py
charts/migrations/__init__.py
charts/templates/charts/base.html
charts/templates/charts/dynchart.html
charts/templates/charts/select_chart.html
charts/templates/charts/tags/config_highcharts.html
charts/templates/charts/tags/load_highcharts_js.html
charts/templates/charts/tags/selector_dropdown.html
charts/templatetags/__init__.py
charts/templatetags/charts_extras.py
acdh_django_charts-0.6.0.dist-info/AUTHORS.rst
acdh_django_charts-0.6.0.dist-info/LICENSE
acdh_django_charts-0.6.0.dist-info/METADATA
acdh_django_charts-0.6.0.dist-info/WHEEL
acdh_django_charts-0.6.0.dist-info/top_level.txt
acdh_django_charts-0.6.0.dist-info/RECORD
